Workbook

Sheet comparison
A17: highest monthly expense: | B17: =MAX(SUMMARY!$B$8:$M$8) -> 15054 | C17: =_xlfn.XLOOKUP(B17,SUMMARY!B8:M8,SUMMARY!B3:M3) -> FEB | I17: highest monthly income: | J17: =MAX(SUMMARY!$B$14:$M$14) -> 31800 | K17: =_xlfn.XLOOKUP(comparison!J17,SUMMARY!B14:M14,SUMMARY!B3:M3) -> MAY
A18: lowest monthly expense: | B18: =MIN(SUMMARY!B8:M8) -> 0 | C18: =_xlfn.XLOOKUP(B18,SUMMARY!B8:M8,SUMMARY!B3:M3) -> JUNE | I18: lowest monthly income: | J18: =MIN(SUMMARY!B14:M14) -> 0 | K18: =_xlfn.XLOOKUP(J18, SUMMARY!B14:M14, SUMMARY!B3:M3) -> MAR
A19: average monthly expense: | B19: =AVERAGE(SUMMARY!B8:M8) -> 3997.4167 | I19: average monthly income: | J19: =AVERAGE(SUMMARY!B14:M14) -> 5407.0833

Sheet SUMMARY
A1: SUMMARY IN AGRICULTURAL WORK 2026
A3: EXPENSES | B3: JAN | C3: FEB | D3: MAR | E3: APR | F3: MAY | G3: JUNE | H3: JULY | I3: AUG | J3: SEPT | K3: OCT | L3: NOV | M3: DEC
A4: seeds | B4: =seeds!K4 -> 375 | C4: =seeds!K5 -> 604 | D4: =seeds!K6 -> 156 | E4: =seeds!K7 -> 0 | F4: =seeds!K8 -> 580 | G4: =seeds!K9 -> 0 | H4: =seeds!K10 -> 0 | I4: =seeds!K11 -> 4480 | J4: =seeds!K12 -> 4080 | K4: =seeds!K13 -> 0 | L4: =seeds!K14 -> 68 | M4: =seeds!K15 -> 7300
A5: insecticides | B5: =insecticides!K4 -> 4500 | C5: =insecticides!K5 -> 1000 | D5: =insecticides!K6 -> 3600 | E5: =insecticides!K7 -> 0 | F5: =insecticides!K8 -> 2000 | G5: =insecticides!K9 -> 0 | H5: =insecticides!K10 -> 0 | I5: =insecticides!K11 -> 0 | J5: =insecticides!K12 -> 0 | K5: =insecticides!K13 -> 0 | L5: =insecticides!K14 -> 0 | M5: =insecticides!K15 -> 0
A6: workers | B6: =workers!G4 -> 2730 | C6: =workers!G5 -> 13400 | D6: =workers!G6 -> 300 | E6: =workers!G7 -> 450 | F6: =workers!G8 -> 1250 | G6: =workers!G9 -> 0 | H6: =workers!G10 -> 0 | I6: =workers!G11 -> 500 | J6: =workers!G12 -> 0 | K6: =workers!G13 -> 0 | L6: =workers!G14 -> 200 | M6: =workers!G15 -> 23
A7: gas | B7: =logistics!J4 -> 112 | C7: =logistics!J5 -> 50 | D7: =logistics!J6 -> 46 | E7: =logistics!J7 -> 0 | F7: =logistics!J8 -> 110 | G7: =logistics!J9 -> 0 | H7: =logistics!J10 -> 0 | I7: =logistics!J11 -> 0 | J7: =logistics!J12 -> 0 | K7: =logistics!J13 -> 55 | L7: =logistics!J14 -> 0 | M7: =logistics!J15 -> 0
A8: total expenses/ month: | B8: =SUM(B4:B7) -> 7717 | C8: =SUM(C4:C7) -> 15054 | D8: =SUM(D4:D7) -> 4102 | E8: =SUM(E4:E7) -> 450 | F8: =SUM(F4:F7) -> 3940 | G8: =SUM(G4:G7) -> 0 | H8: =SUM(H4:H7) -> 0 | I8: =SUM(I4:I7) -> 4980 | ... M8: =SUM(M4:M7) -> 7323
A11: INCOME | B11: JAN | C11: FEB | D11: MAR | E11: APR | F11: MAY | G11: JUNE | H11: JULY | I11: AUG | J11: SEPT | K11: OCT | L11: NOV | M11: DEC
A12: from selling: | B12: =sold!K4 -> 2375 | C12: =sold!K5 -> 1020 | D12: =sold!K6 -> 0 | E12: =sold!K7 -> 0 | F12: =sold!K8 -> 31800 | G12: =sold!K9 -> 7800 | H12: =sold!K10 -> 19250 | I12: =sold!K11 -> 0 | J12: =sold!K12 -> 0 | K12: =sold!K13 -> 0 | L12: =sold!K14 -> 0 | M12: =sold!K15 -> 2640
A13: project:
A14: total income/ month: | B14: =SUM(B12:B13) -> 2375 | C14: =SUM(C12:C13) -> 1020 | D14: =SUM(D12:D13) -> 0 | E14: =SUM(E12:E13) -> 0 | F14: =SUM(F12:F13) -> 31800 | G14: =SUM(G12:G13) -> 7800 | H14: =SUM(H12:H13) -> 19250 | I14: =SUM(I12:I13) -> 0 | ... M14: =SUM(M12:M13) -> 2640
A16: summary:
A17: total expenses in 2026: | B17: =SUM(B8:M8) -> 47969
A18: total income in 2026: | B18: =SUM(B14:M14) -> 64885
A19: profit in agriculture 2026: | B19: =B18-B17 -> 16916

Sheet seeds
A1: SEEDS 2026
A3: month | B3: produce | C3: bought from | D3: nr of packages | E3: seeds/ package | F3: price/ package | G3: final PRICE | H3: price/ seed | J3: monthy expenses on seeds
A4: JAN | B4: tomato cherry | C4: https://www.seminte1.eu/seminte-rosii | D4: 5 | E4: 1000 | F4: 75 | G4: =D4*F4 -> 375 | H4: =F4/E4 -> 0.075 | J4: JAN | K4: =SUMIF(A4:A128,"JAN",G4:G128) -> 375
A5: FEB | B5: salad aletta | C5: https://www.seminte1.eu/seminte-rosii | D5: 6 | E5: 600 | F5: 54 | G5: =D5*F5 -> 324 | H5: =F5/E5 -> 0.09 | J5: FEB | K5: =SUMIF(A4:A129,"FEB",G4:G129) -> 604
A6: FEB | B6: carrot | C6: https://www.seminte1.eu/seminte-rosii | D6: 4 | E6: 400 | F6: 70 | G6: =D6*F6 -> 280 | H6: =F6/E6 -> 0.175 | J6: MAR | K6: =SUMIF(A4:A130,"MAR",G4:G130) -> 156
A7: MAR | B7: cucumber | C7: https://www.seminte1.eu/seminte-rosii | D7: 2 | E7: 3000 | F7: 78 | G7: =D7*F7 -> 156 | H7: =F7/E7 -> 0.026 | J7: APR | K7: =SUMIF(A4:A131,"APR",G4:G131) -> 0
A8: DEC | B8: onion | C8: https://www.seminte1.eu/seminte-rosii | D8: 1 | E8: 300 | F8: 200 | G8: =D8*F8 -> 200 | H8: =F8/E8 -> 0.66666667 | J8: MAY | K8: =SUMIF(A4:A132,"MAY",G4:G132) -> 580
A9: MAY | B9: tomato | C9: https://www.seminte1.eu/seminte-rosii | D9: 1 | E9: 200 | F9: 580 | G9: =D9*F9 -> 580 | H9: =F9/E9 -> 2.9 | J9: JUNE | K9: =SUMIF(A4:A133,"JUNE",G4:G133) -> 0
A10: NOV | B10: salad | C10: https://www.seminte1.eu/seminte-rosii | D10: 2 | E10: 200 | F10: 34 | G10: =D10*F10 -> 68 | H10: =F10/E10 -> 0.17 | J10: JULY | K10: =SUMIF(A4:A134,"JULY",G4:G134) -> 0
A11: DEC | B11: onion | C11: https://www.seminte1.eu/seminte-rosii | D11: 5 | E11: 890 | F11: 340 | G11: =D11*F11 -> 1700 | H11: =F11/E11 -> 0.38202247 | J11: AUG | K11: =SUMIF(A4:A135,"AUG",G4:G135) -> 4480
A12: DEC | B12: spinach | C12: https://www.seminte1.eu/seminte-rosii | D12: 6 | E12: 450 | F12: 900 | G12: =D12*F12 -> 5400 | H12: =F12/E12 -> 2 | J12: SEPT | K12: =SUMIF(A4:A136,"SEPT",G4:G136) -> 4080
A13: AUG | B13: tomato | C13: https://www.seminte1.eu/seminte-rosii | D13: 8 | E13: 34 | F13: 560 | G13: =D13*F13 -> 4480 | H13: =F13/E13 -> 16.470588 | J13: OCT | K13: =SUMIF(A4:A137,"OCT",G4:G137) -> 0
A14: SEPT | B14: cucumber | C14: https://www.seminte1.eu/seminte-rosii | D14: 12 | E14: 1200 | F14: 340 | G14: =D14*F14 -> 4080 | H14: =F14/E14 -> 0.28333333 | J14: NOV | K14: =SUMIF(A4:A138,"NOV",G4:G138) -> 68
G15: =D15*F15 -> 0 | H15: =F15/E15 -> #DIV/0! | J15: DEC | K15: =SUMIF(A4:A139,"DEC",G4:G139) -> 7300
G16: =D16*F16 -> 0 | H16: =F16/E16 -> #DIV/0!
G17: =D17*F17 -> 0 | H17: =F17/E17 -> #DIV/0!
G18: =D18*F18 -> 0 | H18: =F18/E18 -> #DIV/0!
G19: =D19*F19 -> 0 | H19: =F19/E19 -> #DIV/0!
G20: =D20*F20 -> 0 | H20: =F20/E20 -> #DIV/0!
G21: =D21*F21 -> 0 | H21: =F21/E21 -> #DIV/0!
G22: =D22*F22 -> 0 | H22: =F22/E22 -> #DIV/0!
G23: =D23*F23 -> 0 | H23: =F23/E23 -> #DIV/0!
G24: =D24*F24 -> 0 | H24: =F24/E24 -> #DIV/0!
G25: =D25*F25 -> 0 | H25: =F25/E25 -> #DIV/0!
G26: =D26*F26 -> 0 | H26: =F26/E26 -> #DIV/0!
G27: =D27*F27 -> 0 | H27: =F27/E27 -> #DIV/0!
... G128: =D128*F128 -> 0 | H128: =F128/E128 -> #DIV/0!

Sheet insecticides
A1: INSECTICIDES 2026
A3: month | B3: name | C3: bought from | D3: quantity | E3: liters/ product | F3: price/ product | G3: final PRICE | H3: price/ liter | J3: monthy expenses on insecticides
A4: JAN | B4: ortiva top | C4: https://www.botanistii.ro/blog/calendarul-tratamentelor-tomate/ | D4: 2 | E4: 10 | F4: 150 | G4: =D4*F4 -> 300 | H4: =F4/E4 -> 15 | J4: JAN | K4: =SUMIF(A4:A128,"JAN",G4:G128) -> 4500
A5: FEB | B5: amistar | C5: https://www.botanistii.ro/blog/calendarul-tratamentelor-tomate/ | D5: 5 | E5: 60 | F5: 200 | G5: =D5*F5 -> 1000 | H5: =F5/E5 -> 3.3333333 | J5: FEB | K5: =SUMIF(A4:A129,"FEB",G4:G129) -> 1000
A6: MAR | B6: Trica Expert | C6: https://www.botanistii.ro/blog/calendarul-tratamentelor-tomate/ | D6: 4 | E6: 4 | F6: 900 | G6: =D6*F6 -> 3600 | H6: =F6/E6 -> 225 | J6: MAR | K6: =SUMIF(A4:A130,"MAR",G4:G130) -> 3600
A7: MAY | B7: Vertimec | C7: https://www.botanistii.ro/blog/calendarul-tratamentelor-tomate/ | D7: 5 | E7: 5 | F7: 400 | G7: =D7*F7 -> 2000 | H7: =F7/E7 -> 80 | J7: APR | K7: =SUMIF(A4:A131,"APR",G4:G131) -> 0
A8: JAN | B8: Laser 240 | C8: https://www.botanistii.ro/blog/calendarul-tratamentelor-tomate/ | D8: 3 | E8: 6 | F8: 1200 | G8: =D8*F8 -> 3600 | H8: =F8/E8 -> 200 | J8: MAY | K8: =SUMIF(A4:A132,"MAY",G4:G132) -> 2000
A9: JAN | B9: Affirm | C9: https://www.botanistii.ro/blog/calendarul-tratamentelor-tomate/ | D9: 2 | E9: 7 | F9: 300 | G9: =D9*F9 -> 600 | H9: =F9/E9 -> 42.857143 | J9: JUNE | K9: =SUMIF(A4:A133,"JUNE",G4:G133) -> 0
G10: =D10*F10 -> 0 | H10: =F10/E10 -> #DIV/0! | J10: JULY | K10: =SUMIF(A4:A134,"JULY",G4:G134) -> 0
G11: =D11*F11 -> 0 | H11: =F11/E11 -> #DIV/0! | J11: AUG | K11: =SUMIF(A4:A135,"AUG",G4:G135) -> 0
G12: =D12*F12 -> 0 | H12: =F12/E12 -> #DIV/0! | J12: SEPT | K12: =SUMIF(A4:A136,"SEPT",G4:G136) -> 0
G13: =D13*F13 -> 0 | H13: =F13/E13 -> #DIV/0! | J13: OCT | K13: =SUMIF(A4:A137,"OCT",G4:G137) -> 0
G14: =D14*F14 -> 0 | H14: =F14/E14 -> #DIV/0! | J14: NOV | K14: =SUMIF(A4:A138,"NOV",G4:G138) -> 0
G15: =D15*F15 -> 0 | H15: =F15/E15 -> #DIV/0! | J15: DEC | K15: =SUMIF(A4:A139,"DEC",G4:G139) -> 0
G16: =D16*F16 -> 0 | H16: =F16/E16 -> #DIV/0!
G17: =D17*F17 -> 0 | H17: =F17/E17 -> #DIV/0!
G18: =D18*F18 -> 0 | H18: =F18/E18 -> #DIV/0!
G19: =D19*F19 -> 0 | H19: =F19/E19 -> #DIV/0!
G20: =D20*F20 -> 0 | H20: =F20/E20 -> #DIV/0!
G21: =D21*F21 -> 0 | H21: =F21/E21 -> #DIV/0!
G22: =D22*F22 -> 0 | H22: =F22/E22 -> #DIV/0!
G23: =D23*F23 -> 0 | H23: =F23/E23 -> #DIV/0!
G24: =D24*F24 -> 0 | H24: =F24/E24 -> #DIV/0!
G25: =D25*F25 -> 0 | H25: =F25/E25 -> #DIV/0!
G26: =D26*F26 -> 0 | H26: =F26/E26 -> #DIV/0!
G27: =D27*F27 -> 0 | H27: =F27/E27 -> #DIV/0!
... G128: =D128*F128 -> 0 | H128: =F128/E128 -> #DIV/0!

Sheet workers
A1: EXPENSES ON SEASONAL WORKERS 2026
A3: month | B3: day | C3: nr of workers | D3: total paid | F3: monthly expenses on workers
A4: JAN | B4: 24 | C4: 3 | D4: 2500 | F4: JAN | G4: =SUMIF(A4:A200,"JAN",D4:D200) -> 2730
A5: FEB | B5: 23 | C5: 6 | D5: 5600 | F5: FEB | G5: =SUMIF(A4:A200,"FEB",D4:D200) -> 13400
A6: JAN | B6: 12 | C6: 3 | D6: 230 | F6: MAR | G6: =SUMIF(A4:A200,"MAR",D4:D200) -> 300
A7: FEB | B7: 2 | C7: 12 | D7: 7800 | F7: APR | G7: =SUMIF(A4:A200,"APR",D4:D200) -> 450
A8: MAR | B8: 5 | C8: 4 | D8: 300 | F8: MAY | G8: =SUMIF(A4:A200,"MAY",D4:D200) -> 1250
A9: APR | B9: 6 | C9: 5 | D9: 450 | F9: JUNE | G9: =SUMIF(A4:A200,"JUNE",D4:D200) -> 0
A10: DEC | B10: 12 | C10: 2 | D10: 23 | F10: JULY | G10: =SUMIF(A4:A200,"JULY",D4:D200) -> 0
A11: MAY | B11: 23 | C11: 3 | D11: 800 | F11: AUG | G11: =SUMIF(A4:A200,"AUG",D4:D200) -> 500
A12: MAY | B12: 4 | C12: 5 | D12: 450 | F12: SEPT | G12: =SUMIF(A4:A200,"SEPT",D4:D200) -> 0
A13: AUG | B13: 6 | C13: 3 | D13: 500 | F13: OCT | G13: =SUMIF(A4:A200,"OCT",D4:D200) -> 0
A14: NOV | B14: 18 | C14: 1 | D14: 200 | F14: NOV | G14: =SUMIF(A4:A200,"NOV",D4:D200) -> 200
F15: DEC | G15: =SUMIF(A4:A200,"DEC",D4:D200) -> 23

Sheet logistics
A1: PRODUCE TRANSPORTATION 2026
A3: month | B3: day | C3: gas RON | D3: produce name | E3: produce taken kg/sack/box/gathering | F3: unsold produce | G3: percentage sold % | I3: monthly expenses on tranportation
A4: JAN | B4: 3 | C4: 50 | D4: raddish | E4: 500 | F4: 200 | G4: =(100*(E4-F4))/E4 -> 60 | I4: JAN | J4: =SUMIF(A4:A200,"JAN",C4:C200) -> 112
A5: JAN | B5: 23 | C5: 50 | D5: salad | E5: 300 | F5: 0 | G5: =(100*(E5-F5))/E5 -> 100 | I5: FEB | J5: =SUMIF(A4:A200,"FEB",C4:C200) -> 50
A6: FEB | B6: 4 | C6: 50 | D6: raddush | E6: 1500 | F6: 200 | G6: =(100*(E6-F6))/E6 -> 86.666667 | I6: MAR | J6: =SUMIF(A4:A200,"MAR",C4:C200) -> 46
A7: MAY | B7: 5 | C7: 80 | D7: beans | E7: 300 | F7: 1 | G7: =(100*(E7-F7))/E7 -> 99.666667 | I7: APR | J7: =SUMIF(A4:A200,"APR",C4:C200) -> 0
A8: MAR | B8: 12 | C8: 46 | D8: cucumber | E8: 21 | F8: 2 | G8: =(100*(E8-F8))/E8 -> 90.47619 | I8: MAY | J8: =SUMIF(A4:A200,"MAY",C4:C200) -> 110
A9: JAN | B9: 28 | C9: 12 | D9: tomato | E9: 230 | F9: 0 | G9: =(100*(E9-F9))/E9 -> 100 | I9: JUNE | J9: =SUMIF(A4:A200,"JUNE",C4:C200) -> 0
A10: MAY | B10: 12 | C10: 30 | D10: tomato | E10: 1500 | F10: 800 | G10: =(100*(E10-F10))/E10 -> 46.666667 | I10: JULY | J10: =SUMIF(A4:A200,"JULY",C4:C200) -> 0
A11: OCT | B11: 23 | C11: 55 | D11: tomato | E11: 2500 | F11: 500 | G11: =(100*(E11-F11))/E11 -> 80 | I11: AUG | J11: =SUMIF(A4:A200,"AUG",C4:C200) -> 0
G12: =(100*(E12-F12))/E12 -> #DIV/0! | I12: SEPT | J12: =SUMIF(A4:A200,"SEPT",C4:C200) -> 0
G13: =(100*(E13-F13))/E13 -> #DIV/0! | I13: OCT | J13: =SUMIF(A4:A200,"OCT",C4:C200) -> 55
G14: =(100*(E14-F14))/E14 -> #DIV/0! | I14: NOV | J14: =SUMIF(A4:A200,"NOV",C4:C200) -> 0
G15: =(100*(E15-F15))/E15 -> #DIV/0! | I15: DEC | J15: =SUMIF(A4:A200,"DEC",C4:C200) -> 0
G16: =(100*(E16-F16))/E16 -> #DIV/0!
G17: =(100*(E17-F17))/E17 -> #DIV/0!
G18: =(100*(E18-F18))/E18 -> #DIV/0!
G19: =(100*(E19-F19))/E19 -> #DIV/0!
G20: =(100*(E20-F20))/E20 -> #DIV/0!
G21: =(100*(E21-F21))/E21 -> #DIV/0!
G22: =(100*(E22-F22))/E22 -> #DIV/0!
G23: =(100*(E23-F23))/E23 -> #DIV/0!
G24: =(100*(E24-F24))/E24 -> #DIV/0!
G25: =(100*(E25-F25))/E25 -> #DIV/0!
G26: =(100*(E26-F26))/E26 -> #DIV/0!
G27: =(100*(E27-F27))/E27 -> #DIV/0!
... G129: =(100*(E129-F129))/E129 -> #DIV/0!

Sheet sold
A1: INCOME FROM PRODUCE SOLD 2026
A3: month | B3: day | C3: produce name | D3: sold kg/sack/box/gathering | E3: price/kg | F3: price/sack-box | G3: price/gathering | H3: final PRICE | J3: monthy sold products
A4: JAN | B4: 7 | C4: raddish | D4: 500 | E4: 2.5 | H4: =D4*E4+F4*D4+G4*D4 -> 1250 | J4: JAN | K4: =SUMIF(A4:A200,"JAN",H4:H200) -> 2375
A5: FEB | B5: 13 | C5: raddish | D5: 300 | F5: 3.4 | H5: =D5*E5+F5*D5+G5*D5 -> 1020 | J5: FEB | K5: =SUMIF(A4:A200,"FEB",H4:H200) -> 1020
A6: JAN | B6: 20 | C6: salad | D6: 25 | G6: 45 | H6: =D6*E6+F6*D6+G6*D6 -> 1125 | J6: MAR | K6: =SUMIF(A4:A200,"MAR",H4:H200) -> 0
A7: JUNE | B7: 30 | C7: tomato | D7: 1500 | E7: 5.2 | H7: =D7*E7+F7*D7+G7*D7 -> 7800 | J7: APR | K7: =SUMIF(A4:A200,"APR",H4:H200) -> 0
A8: MAY | B8: 10 | C8: cucumber | D8: 1700 | E8: 2.3 | H8: =D8*E8+F8*D8+G8*D8 -> 3910 | J8: MAY | K8: =SUMIF(A4:A200,"MAY",H4:H200) -> 31800
A9: MAY | B9: 2 | C9: raddish | D9: 4000 | E9: 4.5 | H9: =D9*E9+F9*D9+G9*D9 -> 18000 | J9: JUNE | K9: =SUMIF(A4:A200,"JUNE",H4:H200) -> 7800
A10: JULY | B10: 3 | C10: tomato | D10: 3500 | E10: 5.5 | H10: =D10*E10+F10*D10+G10*D10 -> 19250 | J10: JULY | K10: =SUMIF(A4:A200,"JULY",H4:H200) -> 19250
A11: MAY | B11: 13 | C11: tomato | D11: 2300 | E11: 4.3 | H11: =D11*E11+F11*D11+G11*D11 -> 9890 | J11: AUG | K11: =SUMIF(A4:A200,"AUG",H4:H200) -> 0
A12: DEC | B12: 15 | C12: onion | D12: 1200 | G12: 2.2 | H12: =D12*E12+F12*D12+G12*D12 -> 2640 | J12: SEPT | K12: =SUMIF(A4:A200,"SEPT",H4:H200) -> 0
H13: =D13*E13+F13*D13+G13*D13 -> 0 | J13: OCT | K13: =SUMIF(A4:A200,"OCT",H4:H200) -> 0
H14: =D14*E14+F14*D14+G14*D14 -> 0 | J14: NOV | K14: =SUMIF(A4:A200,"NOV",H4:H200) -> 0
H15: =D15*E15+F15*D15+G15*D15 -> 0 | J15: DEC | K15: =SUMIF(A4:A200,"DEC",H4:H200) -> 2640
H16: =D16*E16+F16*D16+G16*D16 -> 0
H17: =D17*E17+F17*D17+G17*D17 -> 0 | J17: total income: | K17: =SUM(K4:K15) -> 64885
H18: =D18*E18+F18*D18+G18*D18 -> 0 | J18: maximum: | K18: =MAX(K4:K15) -> 31800 | L18: =_xlfn.XLOOKUP(K18,K4:K15,J4:J15) -> MAY
H19: =D19*E19+F19*D19+G19*D19 -> 0 | J19: minimum: | K19: =MIN(K4:K15) -> 0 | L19: =_xlfn.XLOOKUP(K19,K4:K15,J4:J15) -> MAR
H20: =D20*E20+F20*D20+G20*D20 -> 0 | J20: monthly average: | K20: =AVERAGE(K4:K15) -> 5407.0833
H21: =D21*E21+F21*D21+G21*D21 -> 0
H22: =D22*E22+F22*D22+G22*D22 -> 0
H23: =D23*E23+F23*D23+G23*D23 -> 0
H24: =D24*E24+F24*D24+G24*D24 -> 0
H25: =D25*E25+F25*D25+G25*D25 -> 0
H26: =D26*E26+F26*D26+G26*D26 -> 0
H27: =D27*E27+F27*D27+G27*D27 -> 0
H28: =D28*E28+F28*D28+G28*D28 -> 0
H29: =D29*E29+F29*D29+G29*D29 -> 0
H30: =D30*E30+F30*D30+G30*D30 -> 0
H31: =D31*E31+F31*D31+G31*D31 -> 0
H32: =D32*E32+F32*D32+G32*D32 -> 0
... H204: =D204*E204+F204*D204+G204*D204 -> 0
